MANIFEST.in
README.md
setup.py
roboticia_first/__init__.py
roboticia_first/_version.py
roboticia_first/roboticia_first.py
roboticia_first.egg-info/PKG-INFO
roboticia_first.egg-info/SOURCES.txt
roboticia_first.egg-info/dependency_links.txt
roboticia_first.egg-info/not-zip-safe
roboticia_first.egg-info/requires.txt
roboticia_first.egg-info/top_level.txt
roboticia_first/configuration/roboticia_first.json
roboticia_first/primitives/__init__.py
roboticia_first/primitives/dance.py
roboticia_first/primitives/mirror.py
roboticia_first/primitives/rest_pos.py
roboticia_first/vrep-scene/roboticia_first.ttt